fps_localspace/__init__.py
fps_localspace/main.py
fps_localspace/micromamba.py
fps_localspace/routes.py
fps_localspace/subprocess.py
fps_localspace/utils.py
fps_localspace-0.0.4.dist-info/METADATA
fps_localspace-0.0.4.dist-info/WHEEL
fps_localspace-0.0.4.dist-info/entry_points.txt
fps_localspace-0.0.4.dist-info/licenses/LICENSE.txt
fps_localspace-0.0.4.dist-info/RECORD
