Metadata-Version: 2.1
Name: fps-localspace
Version: 0.0.4
Project-URL: Documentation, https://github.com/davidbrochart/jupyspace/plugins/fps-localspace#readme
Project-URL: Issues, https://github.com/davidbrochart/jupyspace/plugins/fps-localspace/issues
Project-URL: Source, https://github.com/davidbrochart/jupyspace/plugins/fps-localspace
Author-email: David Brochart <david.brochart@gmail.com>
License: MIT
License-File: LICENSE.txt
Classifier: Development Status :: 4 - Beta
Classifier: Programming Language :: Python
Classifier: Programming Language :: Python :: 3.7
Classifier: Programming Language :: Python :: 3.8
Classifier: Programming Language :: Python :: 3.9
Classifier: Programming Language :: Python :: 3.10
Classifier: Programming Language :: Python :: 3.11
Classifier: Programming Language :: Python :: Implementation :: CPython
Classifier: Programming Language :: Python :: Implementation :: PyPy
Requires-Python: >=3.7
Requires-Dist: httpx
Requires-Dist: jupyspace-api
Requires-Dist: sqlmodel
